tomarkdown/__init__.py
tomarkdown/core.py
tomarkdown/token.py
tomarkdown-0.0.1.dist-info/LICENSE
tomarkdown-0.0.1.dist-info/METADATA
tomarkdown-0.0.1.dist-info/WHEEL
tomarkdown-0.0.1.dist-info/top_level.txt
tomarkdown-0.0.1.dist-info/RECORD
