Metadata-Version: 2.1
Name: tomarkdown
Version: 0.0.1
Summary: support tool to generate MkDocs compatible markdown from python scripts
Home-page: https://gitlab.com/berlinade/tomarkdown
Author: codima
License: GPLv3
Project-URL: doc, https://berlinade.gitlab.io/tomarkdown/
Platform: unix
Platform: linux
Classifier: Development Status :: 3 - Alpha
Classifier: License :: OSI Approved :: GNU General Public License v3 (GPLv3)
Classifier: Operating System :: OS Independent
Classifier: Programming Language :: Python :: 3
Classifier: Programming Language :: Python :: 3 :: Only
Classifier: Programming Language :: Python :: 3.10
Requires-Python: >=3.10
License-File: LICENSE
Requires-Dist: pyyaml
